iseg_nhr/__init__.py
iseg_nhr/channel.py
iseg_nhr/current.py
iseg_nhr/module.py
iseg_nhr/py.typed
iseg_nhr/ramp.py
iseg_nhr/register.py
iseg_nhr/supply.py
iseg_nhr/voltage.py
iseg_nhr-0.1.1.dist-info/LICENSE
iseg_nhr-0.1.1.dist-info/WHEEL
iseg_nhr-0.1.1.dist-info/METADATA
iseg_nhr-0.1.1.dist-info/RECORD
