Metadata-Version: 2.1
Name: iseg-nhr
Version: 0.1.1
Summary: Python interface for an ISEG NHR high-voltage power supply
Home-page: https://github.com/ograsdijk/iseg-nhr
License: MIT
Author: ograsdijk
Author-email: o.grasdijk@gmail.com
Requires-Python: >=3.9,<4.0
Classifier: License :: OSI Approved :: MIT License
Classifier: Programming Language :: Python :: 3
Classifier: Programming Language :: Python :: 3.9
Classifier: Programming Language :: Python :: 3.10
Requires-Dist: PyVISA (>=1.13.0,<2.0.0)
Project-URL: Repository, https://github.com/ograsdijk/iseg-nhr
